superwise/__init__.py
superwise/config.py
superwise/requirements.txt
superwise/controller/__init__.py
superwise/controller/base.py
superwise/controller/dataentity.py
superwise/controller/dataset.py
superwise/controller/infer.py
superwise/controller/model.py
superwise/controller/notification.py
superwise/controller/policy.py
superwise/controller/project.py
superwise/controller/role.py
superwise/controller/segment.py
superwise/controller/summary.py
superwise/controller/transaction.py
superwise/controller/version.py
superwise/controller/summary/__init__.py
superwise/controller/summary/boolean_summary_generator.py
superwise/controller/summary/categorical_summary_generator.py
superwise/controller/summary/entities_validator.py
superwise/controller/summary/entity_summary_generator.py
superwise/controller/summary/feature_importance.py
superwise/controller/summary/numeric_summary_generator.py
superwise/controller/summary/summary.py
superwise/controller/summary/timestamp_summary_generator.py
superwise/controller/summary/unknown_summary_generator.py
superwise/models/__init__.py
superwise/models/base.py
superwise/models/data_entity.py
superwise/models/dataset.py
superwise/models/model.py
superwise/models/notification.py
superwise/models/project.py
superwise/models/role.py
superwise/models/segment.py
superwise/models/transaction.py
superwise/models/validation_error.py
superwise/models/version.py
superwise/resources/__init__.py
superwise/resources/superwise_enums.py
superwise/utils/__init__.py
superwise/utils/client.py
superwise/utils/exceptions.py
superwise/utils/file_path.py
superwise/utils/singelton.py
superwise/utils/storage/__init__.py
superwise/utils/storage/azure_storage.py
superwise/utils/storage/dataframe.py
superwise/utils/storage/gcs.py
superwise/utils/storage/local.py
superwise/utils/storage/s3.py
superwise/utils/storage/internal_storage/__init__.py
superwise/utils/storage/internal_storage/aws.py
superwise/utils/storage/internal_storage/azure.py
superwise-8.2.11.dist-info/LICENCE
superwise-8.2.11.dist-info/METADATA
superwise-8.2.11.dist-info/WHEEL
superwise-8.2.11.dist-info/top_level.txt
superwise-8.2.11.dist-info/RECORD
